reapermc/__init__.py
reapermc/modules/api.bolt
reapermc/modules/core.bolt
reapermc/modules/death_events.bolt
reapermc/modules/defer.bolt
reapermc/modules/effect.bolt
reapermc/modules/entity_nbt.bolt
reapermc/modules/event/on_player_burn.bolt
reapermc/modules/event/on_player_burn_end.bolt
reapermc/modules/event/on_player_burn_start.bolt
reapermc/modules/event/on_player_glide.bolt
reapermc/modules/event/on_player_glide_end.bolt
reapermc/modules/event/on_player_glide_start.bolt
reapermc/modules/event/on_player_inventory_change.bolt
reapermc/modules/event/on_player_join.bolt
reapermc/modules/event/on_player_jump.bolt
reapermc/modules/event/on_player_land.bolt
reapermc/modules/event/on_player_offhand_change.bolt
reapermc/modules/event/on_player_sneak.bolt
reapermc/modules/event/on_player_sneak_end.bolt
reapermc/modules/event/on_player_sneak_start.bolt
reapermc/modules/event/on_player_sprint.bolt
reapermc/modules/event/on_player_sprint_end.bolt
reapermc/modules/event/on_player_sprint_start.bolt
reapermc/modules/event/on_player_swim.bolt
reapermc/modules/event/on_player_swim_end.bolt
reapermc/modules/event/on_player_swim_start.bolt
reapermc/modules/event/on_player_tick.bolt
reapermc/modules/event/on_server_load.bolt
reapermc/modules/event/on_server_tick.bolt
reapermc/modules/event_handler.bolt
reapermc/modules/expr.bolt
reapermc/modules/flag/is_baby.bolt
reapermc/modules/flag/is_gliding.bolt
reapermc/modules/flag/is_in_air.bolt
reapermc/modules/flag/is_on_fire.bolt
reapermc/modules/flag/is_sneaking.bolt
reapermc/modules/flag/is_sprinting.bolt
reapermc/modules/flag/is_swimming.bolt
reapermc/modules/flag_handler.bolt
reapermc/modules/kill.bolt
reapermc/modules/loop.bolt
reapermc/modules/loop_break.bolt
reapermc/modules/loop_cycle.bolt
reapermc/modules/math.bolt
reapermc/modules/scoreboard.bolt
reapermc/modules/sleep.bolt
reapermc/modules/summon.bolt
reapermc/modules/tag.bolt
reapermc/modules/time.bolt
reapermc/modules/util.bolt
reapermc/modules/var.bolt
reapermc-1.5.1.dist-info/METADATA
reapermc-1.5.1.dist-info/WHEEL
reapermc-1.5.1.dist-info/LICENSE
reapermc-1.5.1.dist-info/RECORD
