Metadata-Version: 2.1
Name: reapermc
Version: 1.5.1
Summary: A high level framework for the Bolt scripting language.
Home-page: https://github.com/reapermc/reapermc
License: MIT
Keywords: beet,bolt,minecraft,minecraft-commands,mcfunction,framework,library,reaper,reapermc
Author: Yeti
Author-email: arcticyeti1@gmail.com
Requires-Python: >=3.10,<4.0
Classifier: License :: OSI Approved :: MIT License
Classifier: Programming Language :: Python :: 3
Classifier: Programming Language :: Python :: 3.10
Classifier: Programming Language :: Python :: 3.11
Requires-Dist: beet (>=0.80.1)
Requires-Dist: bolt (>=0.21.0)
Requires-Dist: bolt-expressions (>=0.11.0)
Requires-Dist: mecha (>=0.61.0)
